notionist/__init__.py
notionist/collection_api.py
notionist-0.2.dist-info/LICENSE
notionist-0.2.dist-info/METADATA
notionist-0.2.dist-info/WHEEL
notionist-0.2.dist-info/top_level.txt
notionist-0.2.dist-info/RECORD
