Metadata-Version: 2.1
Name: notionist
Version: 0.2
Summary: Life is divided into before and after meeting Notion
Home-page: https://github.com/TooTouch/notionist
Author: Jaehuck Heo
Author-email: wogur379@gmail.com
License: UNKNOWN
Download-URL: https://github.com/TooTouch/notionist/archive/v0.1.tar.gz
Keywords: notion
Platform: UNKNOWN
Classifier: Programming Language :: Python :: 3
Classifier: Programming Language :: Python :: 3.6
Classifier: Programming Language :: Python :: 3.7
Classifier: Topic :: Software Development :: Libraries :: Python Modules
Requires-Python: >=3.6
Requires-Dist: notion
